{
  "floors": 5,
  "floor_names": [
    "Ogrod",
    "Parter",
    "Nowe pi\u0119tro 2",
    "Nowe pi\u0119tro 3sd",
    "Nowe pi\u0119tro 4"
  ],
  "devices": [
    {
      "name": "sd",
      "type": "bulb",
      "x": 0.7207634759255707,
      "y": 0.2257085020242915,
      "floor": "Ogrod"
    },
    {
      "name": "ds",
      "type": "bulb",
      "x": 0.4369418469646039,
      "y": 0.2846427399058978,
      "floor": "Ogrod"
    },
    {
      "name": "xc",
      "type": "bulb",
      "x": 400,
      "y": 384,
      "floor": null
    },
    {
      "name": "cx",
      "type": "bulb",
      "x": 0.4850926178281096,
      "y": 0.5649469307364045,
      "floor": "Ogrod"
    },
    {
      "name": "xcxxxxxxxxxx",
      "type": "bulb",
      "x": 1,
      "y": 1,
      "floor": null
    },
    {
      "name": "xccxcxcxcx",
      "type": "bulb",
      "x": 400,
      "y": 384,
      "floor": null
    },
    {
      "name": "sssssssssssssssssssssssssssssssssssssssssssssssss",
      "type": "bulb",
      "x": 170,
      "y": 230,
      "floor": "Nowe pi\u0119tro 4"
    },
    {
      "name": "sssssssssssssssssssssssssssssssssssssssssss",
      "type": "bulb",
      "x": 100,
      "y": 100,
      "floor": null
    },
    {
      "name": "ssssssssssssssssssssssssssssssssssssssssssss",
      "type": "bulb",
      "x": 400,
      "y": 384,
      "floor": null
    },
    {
      "name": "sds",
      "type": "bulb",
      "x": 0.5791705704737337,
      "y": 0.4637597111281321,
      "floor": "Ogrod"
    },
    {
      "name": "sd",
      "type": "bulb",
      "x": 400,
      "y": 384,
      "floor": null
    },
    {
      "name": "sd",
      "type": "bulb",
      "x": 400,
      "y": 384,
      "floor": null
    },
    {
      "name": "ffas",
      "type": "bulb",
      "x": 400,
      "y": 384,
      "floor": null
    },
    {
      "name": "1",
      "type": "bulb",
      "x": 400,
      "y": 384,
      "floor": null
    },
    {
      "name": "ssss\\",
      "type": "bulb",
      "x": 0.5,
      "y": 0.5,
      "floor": null
    },
    {
      "name": "sss",
      "type": "bulb",
      "x": 0.5,
      "y": 0.5,
      "floor": null
    },
    {
      "name": "ss",
      "type": "bulb",
      "x": 0.5,
      "y": 0.5,
      "floor": null
    }
  ],
  "backgrounds": {
    "0": "/home/kac/studia/python_syf/jezyki-skryptowe/projekt/icons/camera.png"
  }
}